whikoperator/__init__.py
whikoperator/functions.py
whikoperator/main.py
whikoperator/settings.py
whikoperator/configs/__init__.py
whikoperator/configs/cam_count.py
whikoperator/photos/Tests.png
whikoperator/tests/__init__.py
whikoperator/tests/functions_test.py
whikoperator/tests/main_test.py
whikoperator/tests/settings_test.py
whikoperator/tests/shot_test.py
whikoperator-1.46.dist-info/LICENSE
whikoperator-1.46.dist-info/METADATA
whikoperator-1.46.dist-info/WHEEL
whikoperator-1.46.dist-info/top_level.txt
whikoperator-1.46.dist-info/RECORD
