Metadata-Version: 2.1
Name: whikoperator
Version: 1.46
Author: PunchyArchy
Author-email: ksmdrmvscthny@gmail.com
License-File: LICENSE
Requires-Dist: requests
